{"type":"FeatureCollection","features":[{"type":"Feature","geometry":{"type":"Polygon","coordinates":[[[110.3272498240202,-7.208449936315446,0],[110.2649501894997,-7.204750125417888,0],[110.207349962331,-7.191249953422584,0],[110.1804498909498,-7.169749861267064,0],[110.1339499957957,-7.171849778244621,0],[110.11205015589,-7.145649829076319,0],[110.1421500142118,-7.122549843900117,0],[110.1666497950521,-7.089250197738409,0],[110.1345498436004,-7.06734990727233,0],[110.1142498976147,-7.076049948746118,0],[110.0841500383936,-7.099149933922263,0],[110.0694501707888,-7.118149910789725,0],[110.0490499494956,-7.126949777010566,0],[110.0237502225947,-7.140350125158079,0],[109.9722500968645,-7.147149898249154,0],[109.9521497994737,-7.160850170299057,0],[109.9910499736774,-7.22295015532535,0],[110.0393498619067,-7.260750009005676,0],[110.0513499656285,-7.296350121860598,0],[110.0588498618317,-7.351550057589066,0],[110.0922497824016,-7.403350107221627,0],[110.1736501178587,-7.368450117478915,0],[110.245750113477,-7.357849808521792,0],[110.2976499878567,-7.36105004602274,0],[110.3372498346122,-7.3186501600768,0],[110.3502499844493,-7.259650138143286,0],[110.3272498240202,-7.208449936315446,0]]]},"properties":{"name":" ","styleUrl":"#PolyStyle00","styleHash":"-3dd9574f","description":"<html>\r\n\r\n<head>\r\n\r\n\r\n\r\n\r\n\r\n</head>\r\n\r\n<body>\r\n\r\n<table>\r\n\r\n<tr>\r\n\r\n<td> </td>\r\n\r\n</tr>\r\n\r\n<tr>\r\n\r\n<td>\r\n\r\n<table>\r\n\r\n<tr>\r\n\r\n<td>OBJECTID_1</td>\r\n\r\n<td>2686</td>\r\n\r\n</tr>\r\n\r\n<tr bgcolor=\"#D4E4F3\">\r\n\r\n<td>WorldID</td>\r\n\r\n<td>IDN-JAV-JTE-TEM</td>\r\n\r\n</tr>\r\n\r\n<tr>\r\n\r\n<td>Zone_Name</td>\r\n\r\n<td>Temanggung</td>\r\n\r\n</tr>\r\n\r\n<tr bgcolor=\"#D4E4F3\">\r\n\r\n<td>World</td>\r\n\r\n<td>B</td>\r\n\r\n</tr>\r\n\r\n<tr>\r\n\r\n<td>Adm4ID</td>\r\n\r\n<td></td>\r\n\r\n</tr>\r\n\r\n<tr bgcolor=\"#D4E4F3\">\r\n\r\n<td>Adm3ID</td>\r\n\r\n<td>IDN-JAV-JTE-TEM</td>\r\n\r\n</tr>\r\n\r\n<tr>\r\n\r\n<td>Adm2ID</td>\r\n\r\n<td>IDN-JAV-JTE</td>\r\n\r\n</tr>\r\n\r\n<tr bgcolor=\"#D4E4F3\">\r\n\r\n<td>Adm1ID</td>\r\n\r\n<td>IDN-JAV</td>\r\n\r\n</tr>\r\n\r\n<tr>\r\n\r\n<td>CntyID</td>\r\n\r\n<td>IDN</td>\r\n\r\n</tr>\r\n\r\n<tr bgcolor=\"#D4E4F3\">\r\n\r\n<td>Levels</td>\r\n\r\n<td>3</td>\r\n\r\n</tr>\r\n\r\n<tr>\r\n\r\n<td>Adm4_Name</td>\r\n\r\n<td></td>\r\n\r\n</tr>\r\n\r\n<tr bgcolor=\"#D4E4F3\">\r\n\r\n<td>Adm3_Name</td>\r\n\r\n<td>Temanggung</td>\r\n\r\n</tr>\r\n\r\n<tr>\r\n\r\n<td>Adm2_Name</td>\r\n\r\n<td>Jawa Tengah</td>\r\n\r\n</tr>\r\n\r\n<tr bgcolor=\"#D4E4F3\">\r\n\r\n<td>Adm1_Name</td>\r\n\r\n<td>Java</td>\r\n\r\n</tr>\r\n\r\n<tr>\r\n\r\n<td>Cnty_Name</td>\r\n\r\n<td>Indonesia</td>\r\n\r\n</tr>\r\n\r\n<tr bgcolor=\"#D4E4F3\">\r\n\r\n<td>Composite</td>\r\n\r\n<td>0</td>\r\n\r\n</tr>\r\n\r\n<tr>\r\n\r\n<td>RegionYWAM</td>\r\n\r\n<td>South East Asia and Australia Region</td>\r\n\r\n</tr>\r\n\r\n<tr bgcolor=\"#D4E4F3\">\r\n\r\n<td>GlobalID</td>\r\n\r\n<td>{6961A6CB-C7B4-48B5-868C-4D8A18DCC6C1}</td>\r\n\r\n</tr>\r\n\r\n<tr>\r\n\r\n<td>FieldYWAM</td>\r\n\r\n<td>Asia and Pacific Field</td>\r\n\r\n</tr>\r\n\r\n<tr bgcolor=\"#D4E4F3\">\r\n\r\n<td>Population</td>\r\n\r\n<td>744910.486018</td>\r\n\r\n</tr>\r\n\r\n<tr>\r\n\r\n<td>PopPct</td>\r\n\r\n<td>0.320368</td>\r\n\r\n</tr>\r\n\r\n<tr bgcolor=\"#D4E4F3\">\r\n\r\n<td>Name</td>\r\n\r\n<td></td>\r\n\r\n</tr>\r\n\r\n<tr>\r\n\r\n<td>OZcount</td>\r\n\r\n<td>1</td>\r\n\r\n</tr>\r\n\r\n<tr bgcolor=\"#D4E4F3\">\r\n\r\n<td>Shape_Leng</td>\r\n\r\n<td>1.243535</td>\r\n\r\n</tr>\r\n\r\n<tr>\r\n\r\n<td>Cen_x</td>\r\n\r\n<td>110.154532</td>\r\n\r\n</tr>\r\n\r\n<tr bgcolor=\"#D4E4F3\">\r\n\r\n<td>Cen_y</td>\r\n\r\n<td>-7.250482</td>\r\n\r\n</tr>\r\n\r\n<tr>\r\n\r\n<td>OZ_Label</td>\r\n\r\n<td>Temanggung</td>\r\n\r\n</tr>\r\n\r\n<tr bgcolor=\"#D4E4F3\">\r\n\r\n<td>OZ_Label1</td>\r\n\r\n<td>Temanggung</td>\r\n\r\n</tr>\r\n\r\n</table>\r\n\r\n</td>\r\n\r\n</tr>\r\n\r\n</table>\r\n\r\n</body>\r\n\r\n</html>\r\n\r\n","stroke":"#6e6e6e","stroke-opacity":1,"stroke-width":0.4,"fill":"#c9f5bf","fill-opacity":1},"id":"ID_02717"}],"properties":{"regionKey":"IDN-JAV-JTE-TEM"}}