{"type":"FeatureCollection","features":[{"type":"Feature","geometry":{"type":"Polygon","coordinates":[[[106.8424498026164,-6.520150223653843,0],[106.8383497934083,-6.532250152122799,0],[106.8399501369893,-6.543250208830045,0],[106.842149878714,-6.552850022010887,0],[106.8563501738215,-6.555150038143722,0],[106.8676501544312,-6.552149899797996,0],[106.8731499584039,-6.541250117498862,0],[106.8715500644839,-6.524449882356123,0],[106.8679500783335,-6.519349827032841,0],[106.8580498924886,-6.517850207521008,0],[106.849450125423,-6.521950216729067,0],[106.8424498026164,-6.520150223653843,0]]]},"properties":{"name":" ","styleUrl":"#PolyStyle00","styleHash":"-3dd9574f","description":"<html>\r\n\r\n<head>\r\n\r\n\r\n\r\n\r\n\r\n</head>\r\n\r\n<body>\r\n\r\n<table>\r\n\r\n<tr>\r\n\r\n<td> </td>\r\n\r\n</tr>\r\n\r\n<tr>\r\n\r\n<td>\r\n\r\n<table>\r\n\r\n<tr>\r\n\r\n<td>OBJECTID_1</td>\r\n\r\n<td>2262</td>\r\n\r\n</tr>\r\n\r\n<tr bgcolor=\"#D4E4F3\">\r\n\r\n<td>WorldID</td>\r\n\r\n<td>IDN-JAV-JAW-BOM</td>\r\n\r\n</tr>\r\n\r\n<tr>\r\n\r\n<td>Zone_Name</td>\r\n\r\n<td>Bogor Metro</td>\r\n\r\n</tr>\r\n\r\n<tr bgcolor=\"#D4E4F3\">\r\n\r\n<td>World</td>\r\n\r\n<td>B</td>\r\n\r\n</tr>\r\n\r\n<tr>\r\n\r\n<td>Adm4ID</td>\r\n\r\n<td></td>\r\n\r\n</tr>\r\n\r\n<tr bgcolor=\"#D4E4F3\">\r\n\r\n<td>Adm3ID</td>\r\n\r\n<td>IDN-JAV-JAW-BOM</td>\r\n\r\n</tr>\r\n\r\n<tr>\r\n\r\n<td>Adm2ID</td>\r\n\r\n<td>IDN-JAV-JAW</td>\r\n\r\n</tr>\r\n\r\n<tr bgcolor=\"#D4E4F3\">\r\n\r\n<td>Adm1ID</td>\r\n\r\n<td>IDN-JAV</td>\r\n\r\n</tr>\r\n\r\n<tr>\r\n\r\n<td>CntyID</td>\r\n\r\n<td>IDN</td>\r\n\r\n</tr>\r\n\r\n<tr bgcolor=\"#D4E4F3\">\r\n\r\n<td>Levels</td>\r\n\r\n<td>3</td>\r\n\r\n</tr>\r\n\r\n<tr>\r\n\r\n<td>Adm4_Name</td>\r\n\r\n<td></td>\r\n\r\n</tr>\r\n\r\n<tr bgcolor=\"#D4E4F3\">\r\n\r\n<td>Adm3_Name</td>\r\n\r\n<td>Bogor Metro</td>\r\n\r\n</tr>\r\n\r\n<tr>\r\n\r\n<td>Adm2_Name</td>\r\n\r\n<td>Jawa Barat</td>\r\n\r\n</tr>\r\n\r\n<tr bgcolor=\"#D4E4F3\">\r\n\r\n<td>Adm1_Name</td>\r\n\r\n<td>Java</td>\r\n\r\n</tr>\r\n\r\n<tr>\r\n\r\n<td>Cnty_Name</td>\r\n\r\n<td>Indonesia</td>\r\n\r\n</tr>\r\n\r\n<tr bgcolor=\"#D4E4F3\">\r\n\r\n<td>Composite</td>\r\n\r\n<td>0</td>\r\n\r\n</tr>\r\n\r\n<tr>\r\n\r\n<td>RegionYWAM</td>\r\n\r\n<td>South East Asia and Australia Region</td>\r\n\r\n</tr>\r\n\r\n<tr bgcolor=\"#D4E4F3\">\r\n\r\n<td>GlobalID</td>\r\n\r\n<td>{5EA8BC13-0353-40F7-B7BE-1AA5007863C7}</td>\r\n\r\n</tr>\r\n\r\n<tr>\r\n\r\n<td>FieldYWAM</td>\r\n\r\n<td>Asia and Pacific Field</td>\r\n\r\n</tr>\r\n\r\n<tr bgcolor=\"#D4E4F3\">\r\n\r\n<td>Population</td>\r\n\r\n<td>340284.761314</td>\r\n\r\n</tr>\r\n\r\n<tr>\r\n\r\n<td>PopPct</td>\r\n\r\n<td>0.146348</td>\r\n\r\n</tr>\r\n\r\n<tr bgcolor=\"#D4E4F3\">\r\n\r\n<td>Name</td>\r\n\r\n<td></td>\r\n\r\n</tr>\r\n\r\n<tr>\r\n\r\n<td>OZcount</td>\r\n\r\n<td>1</td>\r\n\r\n</tr>\r\n\r\n<tr bgcolor=\"#D4E4F3\">\r\n\r\n<td>Shape_Leng</td>\r\n\r\n<td>0.121913</td>\r\n\r\n</tr>\r\n\r\n<tr>\r\n\r\n<td>Cen_x</td>\r\n\r\n<td>106.855877</td>\r\n\r\n</tr>\r\n\r\n<tr bgcolor=\"#D4E4F3\">\r\n\r\n<td>Cen_y</td>\r\n\r\n<td>-6.536545</td>\r\n\r\n</tr>\r\n\r\n<tr>\r\n\r\n<td>OZ_Label</td>\r\n\r\n<td>Bogor Metro</td>\r\n\r\n</tr>\r\n\r\n<tr bgcolor=\"#D4E4F3\">\r\n\r\n<td>OZ_Label1</td>\r\n\r\n<td>Bogor Metro</td>\r\n\r\n</tr>\r\n\r\n</table>\r\n\r\n</td>\r\n\r\n</tr>\r\n\r\n</table>\r\n\r\n</body>\r\n\r\n</html>\r\n\r\n","stroke":"#6e6e6e","stroke-opacity":1,"stroke-width":0.4,"fill":"#c9f5bf","fill-opacity":1},"id":"ID_02293"}],"properties":{"regionKey":"IDN-JAV-JAW-BOM"}}