{"type":"FeatureCollection","features":[{"type":"Feature","geometry":{"type":"Polygon","coordinates":[[[105.8449501357403,21.3411497867333,0],[105.7884497794339,21.36524981892404,0],[105.7694498025664,21.32435000215094,0],[105.7567500262928,21.27744990868638,0],[105.7628501277313,21.24204989498674,0],[105.7814499062882,21.19484987761979,0],[105.8002497840004,21.17115004463892,0],[105.7875500077267,21.13604995484161,0],[105.7309498266732,21.11304979441252,0],[105.7118500250587,21.06034997307285,0],[105.7304498036156,20.99555022326422,0],[105.7805501345811,20.96555018968957,0],[105.7930498116995,20.94195018055643,0],[105.8180500643591,20.92984980242648,0],[105.8746497957515,20.92924995462175,0],[105.89365022228,20.97025004670235,0],[105.9440500274869,20.99325020713138,0],[106.0131498847595,20.99834981279366,0],[105.9945501071018,21.05144983244384,0],[105.9505498775749,21.05784985778473,0],[105.925550073677,21.08164996517382,0],[105.9130499468976,21.11114997659018,0],[105.8945499939871,21.17605000080692,0],[105.900950019328,21.20534991216874,0],[105.9261499214817,21.23445017403634,0],[105.9261499214817,21.23835008408918,0],[105.9262501958899,21.2579499087613,0],[105.9012499432304,21.2817500161504,0],[105.8762501393325,21.31145012672204,0],[105.8449501357403,21.3411497867333,0]]]},"properties":{"name":" ","styleUrl":"#PolyStyle00","styleHash":"-3dd9574f","description":"<html>\r\n\r\n<head>\r\n\r\n\r\n\r\n\r\n\r\n</head>\r\n\r\n<body>\r\n\r\n<table>\r\n\r\n<tr>\r\n\r\n<td> </td>\r\n\r\n</tr>\r\n\r\n<tr>\r\n\r\n<td>\r\n\r\n<table>\r\n\r\n<tr>\r\n\r\n<td>OBJECTID_1</td>\r\n\r\n<td>1580</td>\r\n\r\n</tr>\r\n\r\n<tr bgcolor=\"#D4E4F3\">\r\n\r\n<td>WorldID</td>\r\n\r\n<td>VNM-RED-HNO</td>\r\n\r\n</tr>\r\n\r\n<tr>\r\n\r\n<td>Zone_Name</td>\r\n\r\n<td>Ha Noi</td>\r\n\r\n</tr>\r\n\r\n<tr bgcolor=\"#D4E4F3\">\r\n\r\n<td>World</td>\r\n\r\n<td>B</td>\r\n\r\n</tr>\r\n\r\n<tr>\r\n\r\n<td>Adm4ID</td>\r\n\r\n<td></td>\r\n\r\n</tr>\r\n\r\n<tr bgcolor=\"#D4E4F3\">\r\n\r\n<td>Adm3ID</td>\r\n\r\n<td></td>\r\n\r\n</tr>\r\n\r\n<tr>\r\n\r\n<td>Adm2ID</td>\r\n\r\n<td>VNM-RED-HNO</td>\r\n\r\n</tr>\r\n\r\n<tr bgcolor=\"#D4E4F3\">\r\n\r\n<td>Adm1ID</td>\r\n\r\n<td>VNM-RED</td>\r\n\r\n</tr>\r\n\r\n<tr>\r\n\r\n<td>CntyID</td>\r\n\r\n<td>VNM</td>\r\n\r\n</tr>\r\n\r\n<tr bgcolor=\"#D4E4F3\">\r\n\r\n<td>Levels</td>\r\n\r\n<td>2</td>\r\n\r\n</tr>\r\n\r\n<tr>\r\n\r\n<td>Adm4_Name</td>\r\n\r\n<td></td>\r\n\r\n</tr>\r\n\r\n<tr bgcolor=\"#D4E4F3\">\r\n\r\n<td>Adm3_Name</td>\r\n\r\n<td></td>\r\n\r\n</tr>\r\n\r\n<tr>\r\n\r\n<td>Adm2_Name</td>\r\n\r\n<td>Ha Noi</td>\r\n\r\n</tr>\r\n\r\n<tr bgcolor=\"#D4E4F3\">\r\n\r\n<td>Adm1_Name</td>\r\n\r\n<td>Red River Delta</td>\r\n\r\n</tr>\r\n\r\n<tr>\r\n\r\n<td>Cnty_Name</td>\r\n\r\n<td>Vietnam</td>\r\n\r\n</tr>\r\n\r\n<tr bgcolor=\"#D4E4F3\">\r\n\r\n<td>Composite</td>\r\n\r\n<td>0</td>\r\n\r\n</tr>\r\n\r\n<tr>\r\n\r\n<td>RegionYWAM</td>\r\n\r\n<td>Indo-China and the Philippines Region</td>\r\n\r\n</tr>\r\n\r\n<tr bgcolor=\"#D4E4F3\">\r\n\r\n<td>GlobalID</td>\r\n\r\n<td>{970D382B-7BE5-47FE-98BA-DCB228DAC110}</td>\r\n\r\n</tr>\r\n\r\n<tr>\r\n\r\n<td>FieldYWAM</td>\r\n\r\n<td>Asia and Pacific Field</td>\r\n\r\n</tr>\r\n\r\n<tr bgcolor=\"#D4E4F3\">\r\n\r\n<td>Population</td>\r\n\r\n<td>2434866.40225</td>\r\n\r\n</tr>\r\n\r\n<tr>\r\n\r\n<td>PopPct</td>\r\n\r\n<td>2.734914</td>\r\n\r\n</tr>\r\n\r\n<tr bgcolor=\"#D4E4F3\">\r\n\r\n<td>Name</td>\r\n\r\n<td></td>\r\n\r\n</tr>\r\n\r\n<tr>\r\n\r\n<td>OZcount</td>\r\n\r\n<td>1</td>\r\n\r\n</tr>\r\n\r\n<tr bgcolor=\"#D4E4F3\">\r\n\r\n<td>Shape_Leng</td>\r\n\r\n<td>1.276506</td>\r\n\r\n</tr>\r\n\r\n<tr>\r\n\r\n<td>Cen_x</td>\r\n\r\n<td>105.840676</td>\r\n\r\n</tr>\r\n\r\n<tr bgcolor=\"#D4E4F3\">\r\n\r\n<td>Cen_y</td>\r\n\r\n<td>21.119918</td>\r\n\r\n</tr>\r\n\r\n<tr>\r\n\r\n<td>OZ_Label</td>\r\n\r\n<td>Ha Noi</td>\r\n\r\n</tr>\r\n\r\n<tr bgcolor=\"#D4E4F3\">\r\n\r\n<td>OZ_Label1</td>\r\n\r\n<td>Ha Noi</td>\r\n\r\n</tr>\r\n\r\n</table>\r\n\r\n</td>\r\n\r\n</tr>\r\n\r\n</table>\r\n\r\n</body>\r\n\r\n</html>\r\n\r\n","stroke":"#6e6e6e","stroke-opacity":1,"stroke-width":0.4,"fill":"#c9f5bf","fill-opacity":1},"id":"ID_01579"}],"properties":{"regionKey":"VNM-RED-HNO"}}